nchd/__init__.py
nchd/nchd.py
nchd-0.0.2.dist-info/LICENSE
nchd-0.0.2.dist-info/METADATA
nchd-0.0.2.dist-info/WHEEL
nchd-0.0.2.dist-info/entry_points.txt
nchd-0.0.2.dist-info/top_level.txt
nchd-0.0.2.dist-info/RECORD
